pip_test1/__init__.py
pip_test1/add_num.py
pip_test1/maintest.py
pipupload/__init__.py
pipupload/add_num.py
pipupload/maintest.py
pipupload-0.1.3.dist-info/METADATA
pipupload-0.1.3.dist-info/WHEEL
pipupload-0.1.3.dist-info/top_level.txt
pipupload-0.1.3.dist-info/zip-safe
pipupload-0.1.3.dist-info/RECORD
