Metadata-Version: 2.1
Name: pipupload
Version: 0.1.3
Summary: pip_test
Home-page: https://github.com/MrClin/python_pip_install.git
Author: cl
Author-email: cl459134@163.com
License: MIT
Keywords: pip,pip_test,python,layUI
Platform: any
Requires-Python: >=3.5
